DCU_gibic/__init__.py
DCU_gibic/header.py
DCU_gibic-0.1.dist-info/METADATA
DCU_gibic-0.1.dist-info/WHEEL
DCU_gibic-0.1.dist-info/top_level.txt
DCU_gibic-0.1.dist-info/RECORD
