Metadata-Version: 2.1
Name: DCU-gibic
Version: 0.1
Summary: use EASY lib supporting DCU gibic lecture
Home-page: https://github.com/applenongbu/DCU_gibic
Download-URL: https://github.com/applenongbu/DCU_gibic/archive/master.zip
Author: applenongbu
Author-email: hutk1726@naver.com
Keywords: gibic,dcu
Classifier: Programming Language :: Python :: 3
Classifier: Programming Language :: Python :: 3.6
Classifier: Programming Language :: Python :: 3.7
Requires-Python: >=3.6
Requires-Dist: pandas
